example_pkg/__init__.py
example_pkg_eischaefer-0.0.12.dist-info/DESCRIPTION.rst
example_pkg_eischaefer-0.0.12.dist-info/METADATA
example_pkg_eischaefer-0.0.12.dist-info/RECORD
example_pkg_eischaefer-0.0.12.dist-info/WHEEL
example_pkg_eischaefer-0.0.12.dist-info/metadata.json
example_pkg_eischaefer-0.0.12.dist-info/top_level.txt
